fcube_client/__init__.py
fcube_client/auth.py
fcube_client/call.py
fcube_client/collect.py
fcube_client/printer.py
fcube_client-0.1.7.dist-info/METADATA
fcube_client-0.1.7.dist-info/WHEEL
fcube_client-0.1.7.dist-info/entry_points.txt
fcube_client-0.1.7.dist-info/RECORD
